[
  {
    "time": "2006-03-01T00:00:00+00:00",
    "profile_type": "midweek_reversal_short",
    "confidence": 0.75,
    "direction": "short",
    "entry": 1.19358,
    "stop": 1.19399,
    "target": 1.19276,
    "mon_tue_low": 1.18324,
    "mon_tue_high": 1.19399,
    "week_key": [
      2006,
      9
    ]
  },
  {
    "time": "2006-03-09T00:00:00+00:00",
    "profile_type": "consolidation_reversal_long",
    "confidence": 0.7,
    "direction": "long",
    "entry": 1.19349,
    "stop": 1.18669,
    "target": 1.2070899999999998,
    "mon_tue_low": 1.18669,
    "mon_tue_high": 1.20195,
    "week_key": [
      2006,
      10
    ]
  },
  {
    "time": "2006-03-29T00:00:00+00:00",
    "profile_type": "midweek_reversal_short",
    "confidence": 0.75,
    "direction": "short",
    "entry": 1.1996,
    "stop": 1.21046,
    "target": 1.1778799999999998,
    "mon_tue_low": 1.19905,
    "mon_tue_high": 1.21046,
    "week_key": [
      2006,
      13
    ]
  },
  {
    "time": "2006-04-05T00:00:00+00:00",
    "profile_type": "midweek_reversal_long",
    "confidence": 0.75,
    "direction": "long",
    "entry": 1.22451,
    "stop": 1.21192,
    "target": 1.2496899999999997,
    "mon_tue_low": 1.21192,
    "mon_tue_high": 1.22739,
    "week_key": [
      2006,
      14
    ]
  },
  {
    "time": "2006-04-27T00:00:00+00:00",
    "profile_type": "consolidation_reversal_long",
    "confidence": 0.7,
    "direction": "long",
    "entry": 1.24602,
    "stop": 1.23636,
    "target": 1.26534,
    "mon_tue_low": 1.23636,
    "mon_tue_high": 1.24376,
    "week_key": [
      2006,
      17
    ]
  }
]