[
  {
    "time": "2014-03-19T00:00:00+00:00",
    "profile_type": "midweek_reversal_long",
    "confidence": 0.75,
    "direction": "long",
    "entry": 1.393,
    "stop": 1.38791,
    "target": 1.40318,
    "mon_tue_low": 1.38791,
    "mon_tue_high": 1.39475,
    "week_key": [
      2014,
      12
    ]
  },
  {
    "time": "2014-03-26T00:00:00+00:00",
    "profile_type": "midweek_reversal_short",
    "confidence": 0.75,
    "direction": "short",
    "entry": 1.38201,
    "stop": 1.38754,
    "target": 1.37095,
    "mon_tue_low": 1.37491,
    "mon_tue_high": 1.38754,
    "week_key": [
      2014,
      13
    ]
  },
  {
    "time": "2014-04-02T00:00:00+00:00",
    "profile_type": "classic_expansion_short",
    "confidence": 0.85,
    "direction": "short",
    "entry": 1.37963,
    "stop": 1.38155,
    "target": 1.3757899999999996,
    "mon_tue_low": 1.37216,
    "mon_tue_high": 1.38155,
    "week_key": [
      2014,
      14
    ]
  },
  {
    "time": "2014-04-30T00:00:00+00:00",
    "profile_type": "midweek_reversal_long",
    "confidence": 0.75,
    "direction": "long",
    "entry": 1.38096,
    "stop": 1.38055,
    "target": 1.38178,
    "mon_tue_low": 1.38055,
    "mon_tue_high": 1.38794,
    "week_key": [
      2014,
      18
    ]
  },
  {
    "time": "2014-05-28T00:00:00+00:00",
    "profile_type": "midweek_reversal_short",
    "confidence": 0.75,
    "direction": "short",
    "entry": 1.36325,
    "stop": 1.36685,
    "target": 1.3560500000000004,
    "mon_tue_low": 1.36125,
    "mon_tue_high": 1.36685,
    "week_key": [
      2014,
      22
    ]
  },
  {
    "time": "2014-06-18T00:00:00+00:00",
    "profile_type": "midweek_reversal_short",
    "confidence": 0.75,
    "direction": "short",
    "entry": 1.35472,
    "stop": 1.3587,
    "target": 1.3467599999999997,
    "mon_tue_low": 1.3513,
    "mon_tue_high": 1.3587,
    "week_key": [
      2014,
      25
    ]
  },
  {
    "time": "2014-07-02T00:00:00+00:00",
    "profile_type": "midweek_reversal_long",
    "confidence": 0.75,
    "direction": "long",
    "entry": 1.36782,
    "stop": 1.36402,
    "target": 1.37542,
    "mon_tue_low": 1.36402,
    "mon_tue_high": 1.37004,
    "week_key": [
      2014,
      27
    ]
  },
  {
    "time": "2014-07-09T00:00:00+00:00",
    "profile_type": "midweek_reversal_short",
    "confidence": 0.75,
    "direction": "short",
    "entry": 1.36159,
    "stop": 1.36173,
    "target": 1.36131,
    "mon_tue_low": 1.35759,
    "mon_tue_high": 1.36173,
    "week_key": [
      2014,
      28
    ]
  },
  {
    "time": "2014-07-23T00:00:00+00:00",
    "profile_type": "classic_expansion_short",
    "confidence": 0.85,
    "direction": "short",
    "entry": 1.34652,
    "stop": 1.3549,
    "target": 1.3297599999999998,
    "mon_tue_low": 1.3459,
    "mon_tue_high": 1.3549,
    "week_key": [
      2014,
      30
    ]
  },
  {
    "time": "2014-07-30T00:00:00+00:00",
    "profile_type": "midweek_reversal_short",
    "confidence": 0.75,
    "direction": "short",
    "entry": 1.34118,
    "stop": 1.34445,
    "target": 1.3346400000000003,
    "mon_tue_low": 1.34042,
    "mon_tue_high": 1.34445,
    "week_key": [
      2014,
      31
    ]
  },
  {
    "time": "2014-08-13T00:00:00+00:00",
    "profile_type": "midweek_reversal_long",
    "confidence": 0.75,
    "direction": "long",
    "entry": 1.33662,
    "stop": 1.3336,
    "target": 1.34266,
    "mon_tue_low": 1.3336,
    "mon_tue_high": 1.34084,
    "week_key": [
      2014,
      33
    ]
  },
  {
    "time": "2014-08-20T00:00:00+00:00",
    "profile_type": "midweek_reversal_long",
    "confidence": 0.75,
    "direction": "long",
    "entry": 1.33179,
    "stop": 1.33133,
    "target": 1.3327100000000003,
    "mon_tue_low": 1.33133,
    "mon_tue_high": 1.33991,
    "week_key": [
      2014,
      34
    ]
  },
  {
    "time": "2014-08-27T01:00:00+00:00",
    "profile_type": "midweek_reversal_short",
    "confidence": 0.75,
    "direction": "short",
    "entry": 1.31629,
    "stop": 1.32147,
    "target": 1.30593,
    "mon_tue_low": 1.31646,
    "mon_tue_high": 1.32147,
    "week_key": [
      2014,
      35
    ]
  },
  {
    "time": "2014-10-01T00:00:00+00:00",
    "profile_type": "classic_expansion_short",
    "confidence": 0.85,
    "direction": "short",
    "entry": 1.26213,
    "stop": 1.27147,
    "target": 1.2434499999999997,
    "mon_tue_low": 1.2571,
    "mon_tue_high": 1.27147,
    "week_key": [
      2014,
      40
    ]
  },
  {
    "time": "2014-10-08T00:00:00+00:00",
    "profile_type": "classic_expansion_short",
    "confidence": 0.85,
    "direction": "short",
    "entry": 1.26525,
    "stop": 1.26833,
    "target": 1.25909,
    "mon_tue_low": 1.25121,
    "mon_tue_high": 1.26833,
    "week_key": [
      2014,
      41
    ]
  },
  {
    "time": "2014-12-10T00:00:00+00:00",
    "profile_type": "classic_expansion_short",
    "confidence": 0.85,
    "direction": "short",
    "entry": 1.23815,
    "stop": 1.24475,
    "target": 1.2249500000000002,
    "mon_tue_low": 1.22472,
    "mon_tue_high": 1.24475,
    "week_key": [
      2014,
      50
    ]
  }
]