[
  {
    "time": "2011-02-23T00:00:00+00:00",
    "profile_type": "classic_expansion_long",
    "confidence": 0.85,
    "direction": "long",
    "entry": 1.36931,
    "stop": 1.35269,
    "target": 1.4025500000000002,
    "mon_tue_low": 1.35269,
    "mon_tue_high": 1.3703,
    "week_key": [
      2011,
      8
    ]
  },
  {
    "time": "2011-03-30T00:00:00+00:00",
    "profile_type": "classic_expansion_short",
    "confidence": 0.85,
    "direction": "short",
    "entry": 1.40961,
    "stop": 1.41484,
    "target": 1.39915,
    "mon_tue_low": 1.40472,
    "mon_tue_high": 1.41484,
    "week_key": [
      2011,
      13
    ]
  },
  {
    "time": "2011-04-07T00:00:00+00:00",
    "profile_type": "consolidation_reversal_long",
    "confidence": 0.7,
    "direction": "long",
    "entry": 1.43154,
    "stop": 1.41514,
    "target": 1.46434,
    "mon_tue_low": 1.41514,
    "mon_tue_high": 1.42453,
    "week_key": [
      2011,
      14
    ]
  },
  {
    "time": "2011-04-13T00:00:00+00:00",
    "profile_type": "classic_expansion_long",
    "confidence": 0.85,
    "direction": "long",
    "entry": 1.44782,
    "stop": 1.4377,
    "target": 1.4680600000000004,
    "mon_tue_low": 1.4377,
    "mon_tue_high": 1.45185,
    "week_key": [
      2011,
      15
    ]
  },
  {
    "time": "2011-04-27T00:00:00+00:00",
    "profile_type": "classic_expansion_long",
    "confidence": 0.85,
    "direction": "long",
    "entry": 1.46857,
    "stop": 1.4493,
    "target": 1.5071099999999997,
    "mon_tue_low": 1.4493,
    "mon_tue_high": 1.47101,
    "week_key": [
      2011,
      17
    ]
  },
  {
    "time": "2011-05-04T00:00:00+00:00",
    "profile_type": "classic_expansion_long",
    "confidence": 0.85,
    "direction": "long",
    "entry": 1.48283,
    "stop": 1.4754,
    "target": 1.4976900000000002,
    "mon_tue_low": 1.4754,
    "mon_tue_high": 1.48888,
    "week_key": [
      2011,
      18
    ]
  }
]